{
    "CardName": "砂糖",
    "Description": "「没有实战过的牌组不值得判断强度！」",
    "MaxHP": 10,
    "MaxMP": 2,
    "Tags": [
        "蒙德",
        "法器",
        "风元素"
    ],
    "Skills": [
        {
            "CardName": "简式风灵作成",
            "Description": "造成1点风元素伤害。",
            "Category": 0,
            "Cost": "1风2黑",
            "RelatedPersistents": []
        },
        {
            "CardName": "风灵作成·陆叁零捌",
            "Description": "造成3点风元素伤害，对方强制切换到上一个角色。",
            "Category": 1,
            "Cost": "3风",
            "RelatedPersistents": []
        },
        {
            "CardName": "禁·风灵作成·柒伍同构贰型",
            "Description": "造成1点风元素伤害，召唤大型风灵。",
            "Category": 2,
            "Cost": "3风2充",
            "RelatedPersistents": [
                "genshin3_3:summon_sucrose"
            ]
        }
    ]
}