{
    "Type": "Skill",
    "SkillCategory": "Q",
    "Cost": [
        {
            "Type": "Anemo",
            "Count": 4
        },
        {
            "Type": "MP",
            "Count": 2
        }
    ],
    "Action": [
        {
            "Type": "Heal",
            "Heal": {
                "Amount": 2,
                "TargetArea": "TargetExcept",
                "Subheal": {
                    "Amount": 2
                }
            }
        },
        {
            "Type": "Effect",
            "Add": [
                "genshin3_3:summon_jean_q"
            ]
        }
    ]
}